pyctiarbin/__init__.py
pyctiarbin/channel_interface.py
pyctiarbin/cycler_interface.py
pyctiarbin/messages.py
pyctiarbin/arbinspoofer/__init__.py
pyctiarbin/arbinspoofer/arbin_spoofer.py
pycti_arbin-0.0.13.dist-info/LICENSE
pycti_arbin-0.0.13.dist-info/METADATA
pycti_arbin-0.0.13.dist-info/WHEEL
pycti_arbin-0.0.13.dist-info/top_level.txt
pycti_arbin-0.0.13.dist-info/RECORD
