Metadata-Version: 2.1
Name: pycti-arbin
Version: 0.0.13
Summary: A class based Python interface for communication and control of Arbin cyclers over CTI.
Home-page: https://github.com/BattGenie/pycti.git
Author: Zander Nevitt, Bing Syuan Wang
Author-email: info@battgenie.life
Classifier: Programming Language :: Python :: 3
Classifier: License :: OSI Approved :: MIT License
Classifier: Operating System :: OS Independent
Requires-Python: >=3.8
License-File: LICENSE
Requires-Dist: python-dotenv >=1.0.0
Requires-Dist: pydantic >=2.4.2
